{"created_at":"2019-02-23T11:30:06.000Z","id":1099270170101669891,"in_reply_to_screen_name":"MoldAleHouse","in_reply_to_status_id":1099267854841585664,"in_reply_to_user_id":3361364896,"text":"@MoldAleHouse @heavybrew @derventiobrewer @hafodbrewery @ClwydCAMRA @RealAleCymru Do you have a bottle shop?","user_followers_count":561,"user_friends_count":887,"user_id":74325698,"user_screen_name":"tylerfox29"}
{"created_at":"2019-02-24T09:57:40.000Z","id":1099609295535198209,"in_reply_to_screen_name":"ChronicleLive","in_reply_to_status_id":1099589420896923649,"in_reply_to_user_id":19907085,"text":"@ChronicleLive Why are we still talking about this isis bride scum bag! Leave her to rot over their with the rest of her bbf's","user_followers_count":4,"user_friends_count":61,"user_id":1025837515255754753,"user_screen_name":"MartynB73141987"}
{"created_at":"2019-02-24T12:13:39.000Z","id":1099643516748218369,"in_reply_to_screen_name":"ChronicleLive","in_reply_to_status_id":1099589420896923649,"in_reply_to_user_id":19907085,"text":"@ChronicleLive She's enjoying the Isis cock . Leave her there","user_followers_count":9,"user_friends_count":53,"user_id":270406335,"user_screen_name":"dedwards1892"}
{"created_at":"2019-02-24T10:33:29.000Z","id":1099618308633055233,"in_reply_to_screen_name":"ChronicleLive","in_reply_to_status_id":1099589420896923649,"in_reply_to_user_id":19907085,"text":"@ChronicleLive If it was an ISIS man, there would be no questions. He would not be coming home.","user_followers_count":1,"user_friends_count":49,"user_id":1077506829859594240,"user_screen_name":"GeorgeW56641113"}
{"created_at":"2019-02-24T15:39:08.000Z","id":1099695226975858690,"in_reply_to_screen_name":"ChronicleLive","in_reply_to_status_id":1099589420896923649,"in_reply_to_user_id":19907085,"text":"@ChronicleLive Regrets speaking to media ,but says nothing about regrets joining ISIS , you made your decision now stay and rot ,","user_followers_count":59,"user_friends_count":151,"user_id":22382796,"user_screen_name":"navychef"}
{"created_at":"2019-02-24T11:39:03.000Z","id":1099634808211341313,"in_reply_to_screen_name":"ChronicleLive","in_reply_to_status_id":1099589420896923649,"in_reply_to_user_id":19907085,"text":"@ChronicleLive The people who raised her are not her parents and she is an illegal immigrant her father is in Bangl… https://t.co/RuvkBBSS1Z","user_followers_count":35,"user_friends_count":50,"user_id":760173522689912832,"user_screen_name":"BrendaMcArdle1"}
{"created_at":"2019-02-24T08:41:12.000Z","id":1099590052907225089,"in_reply_to_screen_name":"ChronicleLive","in_reply_to_status_id":1099589420896923649,"in_reply_to_user_id":19907085,"text":"@ChronicleLive She ruined her own chances of coming back! Brilliant 🤣","user_followers_count":309,"user_friends_count":2656,"user_id":734283232154423296,"user_screen_name":"nickyBoyle87"}
{"created_at":"2019-02-24T10:57:26.000Z","id":1099624336284139520,"in_reply_to_screen_name":"ChronicleLive","in_reply_to_status_id":1099589420896923649,"in_reply_to_user_id":19907085,"text":"@ChronicleLive You made your bed....Get your head down pet..","user_followers_count":1,"user_friends_count":24,"user_id":952971912786870272,"user_screen_name":"hadtree"}
{"created_at":"2019-02-24T13:27:16.000Z","id":1099662045161709569,"in_reply_to_screen_name":"ChronicleLive","in_reply_to_status_id":1099589420896923649,"in_reply_to_user_id":19907085,"text":"@ChronicleLive Isn’t her dad pals with them who killed rigby","user_followers_count":914,"user_friends_count":1699,"user_id":281482974,"user_screen_name":"frankicoffecake"}
{"created_at":"2019-02-24T14:28:51.000Z","id":1099677539688173571,"in_reply_to_screen_name":"ChronicleLive","in_reply_to_status_id":1099589420896923649,"in_reply_to_user_id":19907085,"text":"@ChronicleLive Why is she getting all this air time, are all you nonces podging her or something.","user_followers_count":19,"user_friends_count":107,"user_id":720992047667277825,"user_screen_name":"biffauk"}
{"created_at":"2019-02-24T11:25:46.000Z","id":1099631466433138688,"in_reply_to_screen_name":"ChronicleLive","in_reply_to_status_id":1099589420896923649,"in_reply_to_user_id":19907085,"text":"@ChronicleLive Sick of hearing about her. Stop giving her airtime!","user_followers_count":12,"user_friends_count":46,"user_id":35517276,"user_screen_name":"pepsi74"}
{"created_at":"2019-02-24T13:25:58.000Z","id":1099661716776992769,"in_reply_to_screen_name":"_Ameera_B","in_reply_to_status_id":1099654276069163008,"in_reply_to_user_id":391100989,"text":"@_Ameera_B Been praying for it to stop https://t.co/o0ShSijqFN","user_followers_count":348,"user_friends_count":422,"user_id":156227441,"user_screen_name":"Kaigamaa"}
{"created_at":"2019-02-24T22:55:05.000Z","id":1099804939650510849,"in_reply_to_screen_name":"Obaa_Hemaaa","in_reply_to_status_id":1099682751211622400,"in_reply_to_user_id":115420948,"text":"@Obaa_Hemaaa @Iambenedicte Soon be hearing congratulations 👏🏾","user_followers_count":155,"user_friends_count":171,"user_id":1032426753308864512,"user_screen_name":"yenistiletto"}
{"created_at":"2019-02-24T22:55:20.000Z","id":1099805002586120195,"in_reply_to_screen_name":"pureblisss_","in_reply_to_status_id":1099803555563749376,"in_reply_to_user_id":859510800360382464,"text":"@pureblisss_ This one wants to do gf giveaway! 😏","user_followers_count":782,"user_friends_count":1528,"user_id":241606938,"user_screen_name":"femipixels"}
{"created_at":"2019-02-25T02:04:10.000Z","id":1099852524037664768,"in_reply_to_screen_name":"thelizlewis","in_reply_to_status_id":1099851005707997184,"in_reply_to_user_id":174916290,"text":"@thelizlewis The plot seemed like it was lost the entire time. Malek was good and the soundy stuff was good","user_followers_count":75,"user_friends_count":759,"user_id":373417096,"user_screen_name":"Col10c"}
{"created_at":"2019-02-26T19:57:30.000Z","id":1100485025085177857,"in_reply_to_screen_name":"stayswithskz","in_reply_to_status_id":1100483481602273280,"in_reply_to_user_id":4902259993,"text":"@stayswithskz I GOT YOU HOMIE 😤🤙🏽","user_followers_count":228,"user_friends_count":271,"user_id":1079139507713306626,"user_screen_name":"spearcb99"}
{"created_at":"2019-02-27T14:50:59.000Z","id":1100770275497373696,"in_reply_to_screen_name":"BenAndWoods","in_reply_to_status_id":1100762696415248384,"in_reply_to_user_id":977963929367277568,"text":"@BenAndWoods @Mighty1090 @Padres Wait 3 wks","user_followers_count":12,"user_friends_count":106,"user_id":2930269814,"user_screen_name":"jopo2811"}
{"created_at":"2019-02-27T15:14:28.000Z","id":1100776182935621633,"in_reply_to_screen_name":"ClickHole","in_reply_to_status_id":1100772598491869184,"in_reply_to_user_id":2377815434,"text":"@ClickHole That's a cool desk.","user_followers_count":44,"user_friends_count":155,"user_id":4434558973,"user_screen_name":"ObiConKnowme"}
{"created_at":"2019-02-27T15:24:14.000Z","id":1100778641129127936,"in_reply_to_screen_name":"ClickHole","in_reply_to_status_id":1100772598491869184,"in_reply_to_user_id":2377815434,"text":"@ClickHole That's a cool desk.","user_followers_count":5,"user_friends_count":25,"user_id":1016647245456904192,"user_screen_name":"Jawdooon"}
{"created_at":"2019-02-27T15:27:00.000Z","id":1100779338507739136,"in_reply_to_screen_name":"ClickHole","in_reply_to_status_id":1100772598491869184,"in_reply_to_user_id":2377815434,"text":"@ClickHole oh wow cool can i sit on it?","user_followers_count":147,"user_friends_count":110,"user_id":303369796,"user_screen_name":"gogobrasil8_br"}
