{"created_at":"2019-05-27T23:39:20.000Z","id":1133155759192100864,"in_reply_to_screen_name":"BayRidgeDrivers","in_reply_to_status_id":1133155071305441280,"in_reply_to_user_id":776100099655081984,"text":"@BayRidgeDrivers \"Police reported that the pedestrian was not in a marked crosswalk when struck by a vehicle.\"","user_followers_count":872,"user_friends_count":349,"user_id":4831407566,"user_screen_name":"skip_sf"}
{"created_at":"2019-05-28T05:58:03.000Z","id":1133251066353504256,"in_reply_to_screen_name":"sheareiswig","in_reply_to_status_id":1133250793706889216,"in_reply_to_user_id":242974135,"text":"@sheareiswig Lying on the TL huh https://t.co/mnjwmgFvA1","user_followers_count":925,"user_friends_count":507,"user_id":36480450,"user_screen_name":"__jazzybunz"}
{"created_at":"2019-05-28T19:18:26.000Z","id":1133452489418825729,"in_reply_to_screen_name":"Surviving_Mars","in_reply_to_status_id":1133425201251852288,"in_reply_to_user_id":861870576452997120,"text":"@Surviving_Mars Nice pic of Utah","user_followers_count":61,"user_friends_count":52,"user_id":1001798989627514880,"user_screen_name":"nicky_mir"}
{"created_at":"2019-05-28T17:52:02.000Z","id":1133430746922848261,"in_reply_to_screen_name":"WorldTruthTV","in_reply_to_status_id":1133430058482307072,"in_reply_to_user_id":21032566,"text":"@WorldTruthTV The people are chemed out spinless almost to the point of zombies now just look at Americas men almost like women now","user_followers_count":0,"user_friends_count":7,"user_id":1133162697472782336,"user_screen_name":"DemonicLandon"}
{"created_at":"2019-05-29T07:53:48.000Z","id":1133642583643762688,"in_reply_to_screen_name":"philbeastall","in_reply_to_status_id":1133439386387976194,"in_reply_to_user_id":2156914979,"text":"@philbeastall @London10K Great blog and race! Looks like team @on_runningUK  are gonna have a mean team at the… https://t.co/4bCpHBYPzF","user_followers_count":2177,"user_friends_count":1645,"user_id":793043434600820736,"user_screen_name":"russell_runner"}
{"created_at":"2019-05-30T09:04:57.000Z","id":1134022877014122497,"in_reply_to_screen_name":"WQuantae","in_reply_to_status_id":1133443433908047872,"in_reply_to_user_id":994322247027511297,"text":"@WQuantae We can help! invoken is a digital agency that does that too! Good prices, excellent results.\ninfo@invoken.com\n416.559.8078","user_followers_count":20,"user_friends_count":3,"user_id":3282573668,"user_screen_name":"invoken_dot_com"}
{"created_at":"2019-05-29T03:02:18.000Z","id":1133569225279332352,"in_reply_to_screen_name":"TommyCarmich","in_reply_to_status_id":1133472747886206976,"in_reply_to_user_id":757560013548359680,"text":"@TommyCarmich Good luck Tommy. And you are ALWAYS a presence.","user_followers_count":909,"user_friends_count":693,"user_id":702538597665284096,"user_screen_name":"MartinJMalcolm"}
{"created_at":"2019-05-28T22:59:06.000Z","id":1133508021982777346,"in_reply_to_screen_name":"shmeatuwu","in_reply_to_status_id":1133503185967099905,"in_reply_to_user_id":1041347574572019714,"text":"@shmeatuwu Thighs&gt;","user_followers_count":9,"user_friends_count":207,"user_id":1017033466016423938,"user_screen_name":"478Bolty"}
{"created_at":"2019-05-29T03:14:16.000Z","id":1133572236793790465,"in_reply_to_screen_name":"geraIdjr","in_reply_to_status_id":1133556214569283590,"in_reply_to_user_id":963643414742028288,"text":"@geraIdjr Where we’re you when I was 19 😭","user_followers_count":1748,"user_friends_count":814,"user_id":55972945,"user_screen_name":"GoldenSogno"}
{"created_at":"2019-05-30T00:48:34.000Z","id":1133897958057844739,"in_reply_to_screen_name":"MechWarriorF2P","in_reply_to_status_id":1133861954131337216,"in_reply_to_user_id":124824260,"text":"@MechWarriorF2P @iammugi this is really lovely!","user_followers_count":589,"user_friends_count":557,"user_id":944468719199068161,"user_screen_name":"tommy_wave"}
{"created_at":"2019-05-30T01:09:28.000Z","id":1133903217694314496,"in_reply_to_screen_name":"ushamirra","in_reply_to_status_id":1133889888208805889,"in_reply_to_user_id":2173082514,"text":"@ushamirra I don’t get “negative integers are not natural numbers”! It’s just the same no’s but on different scales , is it not ?","user_followers_count":427,"user_friends_count":270,"user_id":59316548,"user_screen_name":"Srinathbki"}
{"created_at":"2019-05-30T10:26:58.000Z","id":1134043517184086019,"in_reply_to_screen_name":"MarkYoungTruth","in_reply_to_status_id":1133945420776951808,"in_reply_to_user_id":631310817,"text":"@MarkYoungTruth @chuckwoolery @realDonaldTrump If we had a real press in America, Gore would have won, lol.","user_followers_count":102,"user_friends_count":262,"user_id":24998838,"user_screen_name":"DarinScherer"}
