{"created_at":"2019-03-24T13:32:28.000Z","id":1109810212775428096,"in_reply_to_screen_name":"pinkdogwood770","in_reply_to_status_id":1109809743026155520,"in_reply_to_user_id":17162143,"text":"@pinkdogwood770 No they don't! Isn't collecting benefits more like a vaca? Who needs a job when you can collect benefits. Just ask Moore.","user_followers_count":620,"user_friends_count":1253,"user_id":76509833,"user_screen_name":"hrmcknz"}
{"created_at":"2019-03-24T15:29:34.000Z","id":1109839681976303616,"in_reply_to_screen_name":"borenghosh","in_reply_to_status_id":1109806710531735552,"in_reply_to_user_id":73891492,"text":"@borenghosh We'll check this for you.","user_followers_count":20986,"user_friends_count":6875,"user_id":67537455,"user_screen_name":"makemytripcare"}
{"created_at":"2019-03-24T18:30:02.000Z","id":1109885097891774464,"in_reply_to_screen_name":"davidhogg111","in_reply_to_status_id":1109866752006074368,"in_reply_to_user_id":1915033663,"text":"@davidhogg111 You have no issue getting over the deaths by spewing your, dumb political agenda after more deaths po… https://t.co/yA1g9nz2AV","user_followers_count":84,"user_friends_count":243,"user_id":487174763,"user_screen_name":"J_Raisanen"}
{"created_at":"2019-03-24T19:00:20.000Z","id":1109892723576897537,"in_reply_to_screen_name":"BreitbartNews","in_reply_to_status_id":1109891946267451392,"in_reply_to_user_id":457984599,"text":"@BreitbartNews I feel like if I was sitting in the same room with Bill Maher I would have this erie feeling I'm sit… https://t.co/iL3mz4n2gT","user_followers_count":183,"user_friends_count":72,"user_id":1090731707991552001,"user_screen_name":"R7dotcom"}
{"created_at":"2019-03-24T19:46:03.000Z","id":1109904228124905479,"in_reply_to_screen_name":"RaymondMO2","in_reply_to_status_id":1109901854136254464,"in_reply_to_user_id":581812760,"text":"@RaymondMO2 A cousin is yo Uncle/Aunt's Child\nA niece is yo brother/sister's daughter","user_followers_count":2,"user_friends_count":76,"user_id":1109893770517114880,"user_screen_name":"DidasKarls"}
{"created_at":"2019-03-24T20:24:03.000Z","id":1109913788633866240,"in_reply_to_screen_name":"BreitbartNews","in_reply_to_status_id":1109891946267451392,"in_reply_to_user_id":457984599,"text":"@BreitbartNews Bitter Bill.  Fake news is a real thing...","user_followers_count":15,"user_friends_count":40,"user_id":896232491828166656,"user_screen_name":"SAbstender"}
{"created_at":"2019-03-24T20:41:51.000Z","id":1109918270658883587,"in_reply_to_screen_name":"starsbIush","in_reply_to_status_id":1109916962027520000,"in_reply_to_user_id":874167152852385792,"text":"@starsbIush YOURE SO CUTEEE https://t.co/WpwOBRv0Yj","user_followers_count":449,"user_friends_count":182,"user_id":1088175893657387008,"user_screen_name":"mamoflirt"}
{"created_at":"2019-03-24T21:05:40.000Z","id":1109924265069940736,"in_reply_to_screen_name":"BreitbartNews","in_reply_to_status_id":1109923891399528450,"in_reply_to_user_id":457984599,"text":"@BreitbartNews @Project_Veritas GOPs have turned our Democracy into a  Joke.............","user_followers_count":153,"user_friends_count":925,"user_id":1105115045317369862,"user_screen_name":"SubuMark"}
{"created_at":"2019-03-24T23:12:01.000Z","id":1109956060524101632,"in_reply_to_screen_name":"BreitbartNews","in_reply_to_status_id":1109955543932768256,"in_reply_to_user_id":457984599,"text":"@BreitbartNews @DrewGriffinCNN The ideology of Postmodernism has become cancerous, a malignancy winding its way thr… https://t.co/5zDsXe4ph9","user_followers_count":54,"user_friends_count":151,"user_id":1105273118589825024,"user_screen_name":"WLockwoodAuthor"}
{"created_at":"2019-03-24T23:17:12.000Z","id":1109957366110273536,"in_reply_to_screen_name":"BreitbartNews","in_reply_to_status_id":1109955543932768256,"in_reply_to_user_id":457984599,"text":"@BreitbartNews @DrewGriffinCNN Yes and he proved that the woman was clearly duped by the Russians.","user_followers_count":165,"user_friends_count":998,"user_id":1026627715628056577,"user_screen_name":"Ronald_Truthump"}
{"created_at":"2019-03-24T23:29:13.000Z","id":1109960389737893888,"in_reply_to_screen_name":"BreitbartNews","in_reply_to_status_id":1109955543932768256,"in_reply_to_user_id":457984599,"text":"@BreitbartNews @DrewGriffinCNN How low can cnn go?","user_followers_count":54,"user_friends_count":99,"user_id":1081643726743646209,"user_screen_name":"Oldranchlady"}
{"created_at":"2019-03-25T00:56:51.000Z","id":1109982444193603584,"in_reply_to_screen_name":"TheOnion","in_reply_to_status_id":1109951541090443264,"in_reply_to_user_id":14075928,"text":"@TheOnion Oh,so they've begun tRumps biography already? Great pic of him as a baby.","user_followers_count":2,"user_friends_count":2,"user_id":1091193313359609856,"user_screen_name":"Pendragonk1"}
{"created_at":"2019-03-25T03:59:01.000Z","id":1110028288305565696,"in_reply_to_screen_name":"politicususa","in_reply_to_status_id":1109929528271556614,"in_reply_to_user_id":14792049,"text":"@politicususa he's playing with fire...he just barely escaped criminal charges (more to come though) and feeling fe… https://t.co/25bCNSHg39","user_followers_count":378,"user_friends_count":866,"user_id":64811644,"user_screen_name":"pbh09"}
