{"created_at":"2019-06-15T15:38:00.000Z","id":1139919997113982976,"text":"Trying to be happy and positive BUT people saying “can I get” instead of “I will have” or “I would like to order” give me the hump","user_followers_count":5690,"user_friends_count":3825,"user_id":148317880,"user_screen_name":"forwardnotback"}
{"created_at":"2019-06-15T16:01:46.000Z","id":1139925978187206658,"text":"When giveaways tell me to tag three friends I actually struggle","user_followers_count":1588,"user_friends_count":1297,"user_id":1110902205715005440,"user_screen_name":"___zaynab"}
{"created_at":"2019-06-15T17:29:37.000Z","id":1139948086401359873,"text":"\"RadioActive\" CSGO Edit \n\nhighquality: https://t.co/BT5Gpe07Wb\n\nFollowing back everyone who retweets 🥰 https://t.co/k7fzvv0GOZ","user_followers_count":702,"user_friends_count":331,"user_id":821371637039820801,"user_screen_name":"RevalEdits"}
{"created_at":"2019-06-16T04:08:55.000Z","id":1140108971484823552,"text":"Alhamdu lillaahil-lathee 'ahyaanaa ba'da maa 'amaatanaa wa'ilayhin-nushoor.\n\nPraise is to Allah Who gives us life a… https://t.co/PVZjffKfWs","user_followers_count":12143,"user_friends_count":5323,"user_id":1084351993487994881,"user_screen_name":"TheAeesha"}
{"created_at":"2019-06-16T10:23:36.000Z","id":1140203263632896000,"text":"MY FAV PART IN THE SONG !!!!!!!! cr. owner #GOT7_KEEPSPINNINGinSeoul_Day2 https://t.co/PoC455Bb71","user_followers_count":132,"user_friends_count":109,"user_id":2574454868,"user_screen_name":"gurlzsakinah"}
{"created_at":"2019-06-16T11:53:00.000Z","id":1140225760264777728,"text":"1. “Being a proper workyticket”\nhttps://t.co/XQ3LZVu24j","user_followers_count":183244,"user_friends_count":1360,"user_id":19907085,"user_screen_name":"ChronicleLive"}
{"created_at":"2019-06-16T13:15:10.000Z","id":1140246438791847943,"text":"The only good thing about Trump’s presidency is that he is exposing the Republicans for the win at all costs frauds… https://t.co/WU6mOxA9FC","user_followers_count":69318,"user_friends_count":3995,"user_id":14792049,"user_screen_name":"politicususa"}
{"created_at":"2019-06-16T15:48:14.000Z","id":1140284960299003904,"text":"That was mad wack ma, just move out.","user_followers_count":4543,"user_friends_count":1148,"user_id":1003376605,"user_screen_name":"thegreenranger_"}
{"created_at":"2019-06-16T16:35:58.000Z","id":1140296972781404165,"text":"Wanted https://t.co/ICTblpIoib","user_followers_count":367,"user_friends_count":250,"user_id":1073148670391001088,"user_screen_name":"David_b_almeida"}
{"created_at":"2019-06-16T18:17:34.000Z","id":1140322541174702082,"text":"\"It went very high up in the chain. But you’re going to find that out. I’m not going to make that statement quite y… https://t.co/ryoFqidJHG","user_followers_count":1104917,"user_friends_count":113,"user_id":457984599,"user_screen_name":"BreitbartNews"}
{"created_at":"2019-06-16T20:52:20.000Z","id":1140361489586556935,"text":"Happy daddies day everyone! Send your daddy some love ! @petemastersXXX @RealMenFullBush https://t.co/DzrXBo1ZoE","user_followers_count":14354,"user_friends_count":575,"user_id":947994250049916928,"user_screen_name":"BobSteelXXX"}
{"created_at":"2019-06-16T22:06:23.000Z","id":1140380124853886976,"text":"tsunade when shizune's out https://t.co/eBjL37BiTN","user_followers_count":1807,"user_friends_count":258,"user_id":1101304187583754240,"user_screen_name":"senjuslut"}
{"created_at":"2019-06-16T22:37:48.000Z","id":1140388031138029573,"text":"Retweet if you wanna Save the Princess ❤️\n\nFull Normal + Boudoir sets on Patreon TIER 3 this month 💖… https://t.co/iPHqTeZo4z","user_followers_count":51391,"user_friends_count":108,"user_id":1043079362,"user_screen_name":"Merylsama"}
{"created_at":"2019-06-16T23:48:32.000Z","id":1140405831747416064,"text":"Watch Harry play for Team U.K. on #LateLateLondon's Dodgeball segment tomorrow, Monday 17th, at 11:37pm CT on CBS… https://t.co/whQHZvLrm2","user_followers_count":94512,"user_friends_count":13,"user_id":1561975297,"user_screen_name":"hsdaily"}
{"created_at":"2019-06-17T00:13:05.000Z","id":1140412009953071104,"text":"can anyone who thinks trump is worse than bush please consider the one million people dead in Iraq please and thank you","user_followers_count":146,"user_friends_count":569,"user_id":1045497921096077313,"user_screen_name":"mothconnoissuer"}
{"created_at":"2019-06-17T01:41:55.000Z","id":1140434365614317568,"text":"Love how he puts me on new music and they’re usually 🔥","user_followers_count":227,"user_friends_count":214,"user_id":2190823705,"user_screen_name":"deshawnabegay"}
{"created_at":"2019-06-17T07:00:31.000Z","id":1140514543925260288,"text":"THIS CURSED IMAGE...... I LOVE IT https://t.co/46HKjEJD3f","user_followers_count":13669,"user_friends_count":204,"user_id":3288426902,"user_screen_name":"ultseul"}
{"created_at":"2019-06-17T11:03:09.000Z","id":1140575604573708295,"text":"To think at once there was Branislav Ivanovic and Eden Hazard on the same wing. Ass everywhere. Like watching a brazzers video","user_followers_count":45947,"user_friends_count":291,"user_id":1061250879028973568,"user_screen_name":"jmemc55"}
{"created_at":"2019-06-17T11:42:08.000Z","id":1140585415063343104,"text":"Mood because the #YNTCDmusicvideo drops in 35 MINS !!! @taylornation13 @taylorswift13 https://t.co/pX1yktceZE","user_followers_count":112,"user_friends_count":170,"user_id":957712122145845248,"user_screen_name":"taylormoments13"}
{"created_at":"2019-06-17T12:35:55.000Z","id":1140598950069772288,"text":"GlobeX Wallet is out🔥\n\nHere is the look of our fresh and powered wallet, that anyone can use now with FIAT EXCHANGE… https://t.co/MtuMFQo0c8","user_followers_count":3165,"user_friends_count":59,"user_id":1052960466270658561,"user_screen_name":"GlobeXToken"}
{"created_at":"2019-06-17T13:14:29.000Z","id":1140608655689211905,"text":"What Should We Play Next? #NP 'See' by @DamiOniru Ft @RemyBaggins #MiddayShowWithToolzandNadine","user_followers_count":2032226,"user_friends_count":8858,"user_id":52833129,"user_screen_name":"THEBEAT999FM"}
{"created_at":"2019-06-17T13:30:00.000Z","id":1140612560598650882,"text":"How Many Followers You Want?\n\n1000 Retweet = 1000 Followers\n\n2000 Retweet = 2000 Followers\n\n3000 Retweet = 3000 Fol… https://t.co/f8EvcYpIQ4","user_followers_count":154644,"user_friends_count":61875,"user_id":4604792239,"user_screen_name":"farahelp"}
{"created_at":"2019-06-17T13:40:56.000Z","id":1140615312058007552,"text":"Today and Wednesday only, @EmanuelTheMovie will be in theaters nationwide. Proceeds will go to the victims' familie… https://t.co/RoSrBfKFFx","user_followers_count":1670,"user_friends_count":1996,"user_id":20184785,"user_screen_name":"teddy_kulmala"}
{"created_at":"2019-06-17T15:28:29.000Z","id":1140642377897369600,"text":"Oops 👀 https://t.co/GHU49kfvL6","user_followers_count":197813,"user_friends_count":0,"user_id":4709720570,"user_screen_name":"bustygirlshq"}
{"created_at":"2019-06-17T16:03:58.000Z","id":1140651307583148032,"text":"Moto of my DP 🔥\n\nOne man against all odds 🙏\n\nRemember the name Super Star Mahesh Babu 😎 https://t.co/3xRQjHANrz","user_followers_count":490,"user_friends_count":587,"user_id":2889831840,"user_screen_name":"iamPavanRayudu"}
{"created_at":"2019-06-17T18:02:27.000Z","id":1140681124903038976,"text":"“The Quran is our constitution, The Prophet Muhammad [SAW] is our leader, Jihad is our path, and death for the sake… https://t.co/sy95XLLHmL","user_followers_count":30363,"user_friends_count":97,"user_id":267835652,"user_screen_name":"KhanDanish_"}
{"created_at":"2019-06-17T18:12:51.000Z","id":1140683742144585728,"text":"LMAOOOOOOO wat he dancing wit? https://t.co/isg9EIU5qO","user_followers_count":8332,"user_friends_count":87,"user_id":728368745819701249,"user_screen_name":"Tabondarun"}
