{"created_at":"2019-05-27T18:54:36.000Z","id":1133084103694331907,"text":"This article/discussion is well worth your time.  https://t.co/kqoJQVsHS1","user_followers_count":217766,"user_friends_count":4516,"user_id":2889924959,"user_screen_name":"TrueFactsStated"}
{"created_at":"2019-05-27T20:07:55.000Z","id":1133102554446028800,"text":"I swear once you settle into a style, your art gets worse for a while as you figure out which shortcuts work for you and which ones don’t","user_followers_count":34616,"user_friends_count":1430,"user_id":103213895,"user_screen_name":"Trungles"}
{"created_at":"2019-05-27T20:23:17.000Z","id":1133106421585895424,"text":"A+ for Creativity via _youhadonejob1 #education #edchat https://t.co/IqsIrWXkWa","user_followers_count":74907,"user_friends_count":98217,"user_id":1623145514,"user_screen_name":"Britanniacomms"}
{"created_at":"2019-05-28T01:49:52.000Z","id":1133188608960151552,"text":"ALL HUSTLE","user_followers_count":35402,"user_friends_count":1140,"user_id":28226601,"user_screen_name":"IAMDJJUS"}
{"created_at":"2019-05-28T02:59:21.000Z","id":1133206095034494976,"text":"A fruit salad sounds good rn","user_followers_count":4841,"user_friends_count":1302,"user_id":1683983298,"user_screen_name":"heyits_samara"}
{"created_at":"2019-05-28T03:36:10.000Z","id":1133215360252108800,"text":"So, the illegal alien who abducted and raped a 15-year-old New Jersey girl in April did not commit a crime?… https://t.co/6ZeIs3hybV","user_followers_count":101799,"user_friends_count":803,"user_id":129571843,"user_screen_name":"RealKyleMorris"}
{"created_at":"2019-05-28T11:15:48.000Z","id":1133331030751031296,"text":"Beatrice Williams is a Welsh artist so Bore Da to all our friends in Wales.  Wish we were there seems  an appropria… https://t.co/t67KOqikVu","user_followers_count":48481,"user_friends_count":22929,"user_id":2328834820,"user_screen_name":"HWarlow"}
{"created_at":"2019-05-28T12:28:11.000Z","id":1133349246600663040,"text":"[#MEDIA] 📺 Alain Guillou unveiled shortlist for Start We Up, our innovation challenge during @IMDEXAsia. Congratula… https://t.co/FK4stFHZus","user_followers_count":12517,"user_friends_count":582,"user_id":191076590,"user_screen_name":"navalgroup"}
{"created_at":"2019-05-28T12:39:48.000Z","id":1133352170043203585,"text":"Old column for context on 19th century Indian history.\n\nBrits used punitive taxation and suppression of investments… https://t.co/jjUt0AmB2h","user_followers_count":21880,"user_friends_count":52,"user_id":3405760034,"user_screen_name":"subhashkak1"}
{"created_at":"2019-05-28T14:03:30.000Z","id":1133373233846214656,"text":"First of last year’s draft picks to sign a NWHL contract. ✅","user_followers_count":606,"user_friends_count":443,"user_id":40092695,"user_screen_name":"strongforecheck"}
{"created_at":"2019-05-28T14:27:01.000Z","id":1133379152017592323,"text":"Ronaldo is doing barber in Bodija and you’re complaining. Drop your shoulders abeg 🥴","user_followers_count":9315,"user_friends_count":8898,"user_id":349633754,"user_screen_name":"Uzz_HRH"}
{"created_at":"2019-05-28T19:30:00.000Z","id":1133455398462218241,"text":"The rich truly believe they can get away with anything.","user_followers_count":482062,"user_friends_count":15,"user_id":2377815434,"user_screen_name":"ClickHole"}
{"created_at":"2019-05-28T19:31:47.000Z","id":1133455849035390977,"text":"Apple Maps defaults to driving directions, and even after explicitly switching to walking directions, it will quiet… https://t.co/uVokMJ9cWK","user_followers_count":366,"user_friends_count":144,"user_id":29492746,"user_screen_name":"pndc"}
{"created_at":"2019-05-28T20:44:14.000Z","id":1133474081708421121,"text":"This could be lethal ...Bluegill? 🔮 @ETC_HS0 https://t.co/1Vqj1HxZe3","user_followers_count":39574,"user_friends_count":162,"user_id":816711729581158400,"user_screen_name":"HSesports"}
{"created_at":"2019-05-28T23:30:08.000Z","id":1133515831806169088,"text":"Patience is when you’re supposed to be mad but you choose to understand.","user_followers_count":3034505,"user_friends_count":27783,"user_id":396086694,"user_screen_name":"ItsLifeFact"}
{"created_at":"2019-05-29T01:31:57.000Z","id":1133546487952994304,"text":"P’Nom:\n\nGun - Pi, don’t post this (Kill This Love dance video). I’m ugly.\nPP - :) Select ‘your story’ button… https://t.co/7A6QX18Vt6","user_followers_count":1085,"user_friends_count":72,"user_id":1085595021477199872,"user_screen_name":"quentin_holmes"}
{"created_at":"2019-05-29T05:07:37.000Z","id":1133600762234331136,"text":"I'm trying to start a small movement here. Let's see how it goes.\nIn last couple of months we had some amazing peop… https://t.co/XPHkOZHABE","user_followers_count":10530,"user_friends_count":345,"user_id":145971970,"user_screen_name":"rj_kulsoom"}
{"created_at":"2019-05-29T10:32:12.000Z","id":1133682446308745216,"text":"#ADNFriendsToKeep 😘\n@lynieg88 @Darwaine88 @carl05290 \nLife is like a book; don?T jump to the end to see if it?S wor… https://t.co/As3C6DkdqP","user_followers_count":4989,"user_friends_count":2688,"user_id":3272677566,"user_screen_name":"montenegro_emil"}
{"created_at":"2019-05-29T13:02:07.000Z","id":1133720172563456005,"text":"Little Pussy Has To Take Phone Call In Other Room https://t.co/UPhf0W1nA0 https://t.co/0wl0EVt8IT","user_followers_count":11159317,"user_friends_count":15,"user_id":14075928,"user_screen_name":"TheOnion"}
{"created_at":"2019-05-29T14:14:55.000Z","id":1133738494789115904,"text":"Coconut water taste like somebody drunk regular water then spit it back in the bottle.","user_followers_count":680,"user_friends_count":582,"user_id":99630143,"user_screen_name":"MardyMarvel"}
{"created_at":"2019-05-29T15:32:10.000Z","id":1133757935392366592,"text":"Ronald Reagan criticizes US policies in 1979 👇. After #40YearsOfFailure of Mullah’s regime in Iran it does not make… https://t.co/wRyYK1M8zU","user_followers_count":2456,"user_friends_count":1741,"user_id":2871004738,"user_screen_name":"PanteaPeyvandi"}
{"created_at":"2019-05-29T21:02:38.000Z","id":1133841100081455105,"text":"PLEASE DON’T LET ME BE KILLED! #dogsarejoy #animallovers #dogsoftwitter #dogsarelove #dogsarefamily #AdoptDontShop… https://t.co/AlGf21ncJI","user_followers_count":509,"user_friends_count":615,"user_id":882732343496192000,"user_screen_name":"solitarymagpie"}
{"created_at":"2019-05-29T22:38:23.000Z","id":1133865196328574978,"text":"I admit i got alot of growin up to do","user_followers_count":2747,"user_friends_count":1372,"user_id":1569344816,"user_screen_name":"OneandOnlyDee22"}
{"created_at":"2019-05-29T23:16:18.000Z","id":1133874738386939905,"text":"Cook dinner.","user_followers_count":21248,"user_friends_count":2601,"user_id":33243882,"user_screen_name":"KingThelonious"}
{"created_at":"2019-05-30T01:41:58.000Z","id":1133911396603686913,"text":"Good morning Admin klo!!\n#WeMissViceJack \n#ShowtimeBuklod","user_followers_count":772,"user_friends_count":1105,"user_id":996467794022563842,"user_screen_name":"nackate34vjb"}
{"created_at":"2019-05-30T10:22:36.000Z","id":1134042418289029121,"text":"KH Days' anniversary is Xion's birthday by default, until proven otherwise! Happy birthday, kiddo!! 🎂\n#XionLives https://t.co/DB1A0HaFiA","user_followers_count":437,"user_friends_count":148,"user_id":836528884644515840,"user_screen_name":"shompsketch"}
