{"created_at":"2019-02-23T10:33:27.000Z","id":1099255913658101760,"text":"take me anywhere away with you ✨","user_followers_count":1745,"user_friends_count":382,"user_id":184479189,"user_screen_name":"yara4__"}
{"created_at":"2019-02-23T11:00:18.000Z","id":1099262670677659648,"text":"When Treacle went into rescue in Carmarthen she was clearly neglected. \nA few weeks on she looks much better.   She… https://t.co/8Ir6OS3ZNS","user_followers_count":40444,"user_friends_count":9128,"user_id":999015600,"user_screen_name":"NWDogRescue"}
{"created_at":"2019-02-23T12:42:16.000Z","id":1099288331433717760,"text":"Do you want more followers??\n\nRETWEET RETWEET\n\nFOLLOW ALL THAT RETWEET\n\nFOLLOW BACK ALL THAT FOLLOWS YOU\n\nTURN ON MY NOTIFICATION!!!","user_followers_count":1444,"user_friends_count":728,"user_id":1090156388561666048,"user_screen_name":"realDoubleKayy"}
{"created_at":"2019-02-24T01:02:01.000Z","id":1099474496224940032,"text":"Connecticut Democrat resigned after discovery of his secret ‘furries’ fetish - https://t.co/C1OxkhgaXn","user_followers_count":14881,"user_friends_count":2409,"user_id":76227785,"user_screen_name":"DCClothesline"}
{"created_at":"2019-02-24T09:18:44.000Z","id":1099599498463068165,"text":"mini cornfield    Collagraph by @cathoneillhouse via @artfinder #collagraph #print #art https://t.co/DnbG93SzB1… https://t.co/lpdYnvNRnG","user_followers_count":472,"user_friends_count":319,"user_id":3187805639,"user_screen_name":"cathoneillhouse"}
{"created_at":"2019-02-24T15:35:21.000Z","id":1099694277142237185,"text":"Wait, women genuinely enjoy hearing us vent?","user_followers_count":10741,"user_friends_count":471,"user_id":175233711,"user_screen_name":"NY_Wiseass"}
{"created_at":"2019-02-24T15:44:37.000Z","id":1099696609179459584,"text":"\"Girls just want to have fun.\" @bernardokath ❤ https://t.co/2DQBcrjHZT","user_followers_count":28023,"user_friends_count":271,"user_id":470032644,"user_screen_name":"jochendria"}
{"created_at":"2019-02-24T17:05:11.000Z","id":1099716885422268416,"text":"#SundayWire LIVE Coming Up... 'Say Hello to My Little Friend’ @21WIRE @RadioACR - https://t.co/wmnEl18L14","user_followers_count":26098,"user_friends_count":1897,"user_id":16936686,"user_screen_name":"21WIRE"}
{"created_at":"2019-02-24T19:03:26.000Z","id":1099746643052806145,"text":"Gonna need 5 penalty saves from kepa in this shootout to save an ear bashing from sarri 🤣","user_followers_count":221837,"user_friends_count":246,"user_id":369758604,"user_screen_name":"BenFoster"}
{"created_at":"2019-02-25T00:55:03.000Z","id":1099835130288340992,"text":"Bearcats win game 3 10-5 and win the series. Home runs by Connor Bailey, Cole Pursell (2), and Eric Waldichuk and 5… https://t.co/7nWW7AXFk7","user_followers_count":1013,"user_friends_count":116,"user_id":2345725928,"user_screen_name":"WillametteBSB"}
{"created_at":"2019-02-25T04:34:51.000Z","id":1099890444736040962,"text":"When you realize that ain’t your Uber  https://t.co/mFN0pr8Sbk","user_followers_count":54756,"user_friends_count":28182,"user_id":4728889702,"user_screen_name":"BIackPplVids"}
{"created_at":"2019-02-25T10:30:54.000Z","id":1099980047652253700,"text":"“Drinking water is like washing out your insides. The water will cleanse the system, fill you up, decrease your cal… https://t.co/DQ4uX9GWfA","user_followers_count":2847,"user_friends_count":500,"user_id":40160932,"user_screen_name":"reallyrabbit"}
{"created_at":"2019-02-25T14:15:44.000Z","id":1100036628817547269,"text":"the anatomy of rdj ࿐ https://t.co/Tg6QZsvG1q","user_followers_count":97,"user_friends_count":69,"user_id":1079913618009964544,"user_screen_name":"syntetyzm"}
{"created_at":"2019-02-25T19:29:03.000Z","id":1100115477723054082,"text":"It was only a matter of time. Blair's #Brexit ploy seems to have worked. Labour goes for Ireland model, backs a Sec… https://t.co/7sXvkX4Pka","user_followers_count":26145,"user_friends_count":1904,"user_id":16936686,"user_screen_name":"21WIRE"}
{"created_at":"2019-02-27T15:55:19.000Z","id":1100786463350898692,"text":"New report from @project_veritas and @JamesOkeefeIII from a Facebook insider sounds strikingly similar to the \"blac… https://t.co/qpWbmpQjlf","user_followers_count":1060889,"user_friends_count":113,"user_id":457984599,"user_screen_name":"BreitbartNews"}
