{"created_at":"2019-05-27T16:08:46.000Z","id":1133042370369466370,"text":"Another sale!!! AJ May Suck Fuck and Cum by simonsimpler @manyvids https://t.co/qHjV5u38jB","user_followers_count":1901,"user_friends_count":4577,"user_id":904924424582955008,"user_screen_name":"simonsimplerxx"}
{"created_at":"2019-05-27T16:44:57.000Z","id":1133051476211847169,"text":"coloured hijabs all summer!","user_followers_count":777,"user_friends_count":315,"user_id":949765607020552192,"user_screen_name":"sagaaalx"}
{"created_at":"2019-05-27T17:07:56.000Z","id":1133057260144517127,"text":"Melinda, a great info tweet! Mr. Corbyn is really quite the fence stradler isn't he? These statist, globalist, quas… https://t.co/rAWTqE81GM","user_followers_count":21399,"user_friends_count":21814,"user_id":3711605968,"user_screen_name":"kbrunorunner"}
{"created_at":"2019-05-27T19:39:57.000Z","id":1133095516399656960,"text":"on every level except physical, i am jimin https://t.co/Onlu35ProA","user_followers_count":809,"user_friends_count":171,"user_id":1007066801421848576,"user_screen_name":"doughnutbts"}
{"created_at":"2019-05-28T08:25:58.000Z","id":1133288290788921349,"text":"#Visakhapatnam AP 1 Unit A+ve #Blood #Urgent #Need at Apollo Hospital Arilova Pls Call 09398202209 #May_28… https://t.co/3ExSTzFVLr","user_followers_count":23425,"user_friends_count":119,"user_id":3322568239,"user_screen_name":"bld4needy"}
{"created_at":"2019-05-28T09:55:59.000Z","id":1133310944229175296,"text":"Noooooo! Thank you! I was talking abt my weighted blanket yesterday and telling everybody abt how YOU changed my li… https://t.co/8GYOiCJE2G","user_followers_count":1235,"user_friends_count":822,"user_id":24231237,"user_screen_name":"EbonyJanice"}
{"created_at":"2019-05-28T14:36:10.000Z","id":1133381454694633472,"text":"ricky dillon is the epitome of a local who thinks they’re not a local","user_followers_count":259,"user_friends_count":350,"user_id":1044630262620069888,"user_screen_name":"missnorthkorea"}
{"created_at":"2019-05-28T20:20:45.000Z","id":1133468171153727489,"text":"Breaking: https://t.co/C0GLK6r5yZ","user_followers_count":1099959,"user_friends_count":113,"user_id":457984599,"user_screen_name":"BreitbartNews"}
{"created_at":"2019-05-28T21:24:29.000Z","id":1133484210918973441,"text":"Massie is acting childish at best and heartless at worse. He’s an absolute clown.","user_followers_count":2520,"user_friends_count":916,"user_id":191988816,"user_screen_name":"WillKremer"}
{"created_at":"2019-05-28T22:01:31.000Z","id":1133493530675089414,"text":"Men get regularly called out regarding porn, yet women do not. \nI’m not referring to digital porn, I’m speaking of… https://t.co/QtPJz8tlUn","user_followers_count":3546,"user_friends_count":215,"user_id":180239936,"user_screen_name":"fiercelyfeminin"}
{"created_at":"2019-05-28T22:13:48.000Z","id":1133496621868539904,"text":"somewhere between I want it &amp; I got it 💙  #prom2k19 https://t.co/wvIX3CgS9w","user_followers_count":871,"user_friends_count":754,"user_id":2614947271,"user_screen_name":"bcimlex"}
{"created_at":"2019-05-28T23:34:33.000Z","id":1133516943271571464,"text":"Martin Scorsese directing The Wolf of Wall Street https://t.co/uQFttWxff2","user_followers_count":111905,"user_friends_count":74,"user_id":1046451702,"user_screen_name":"ActorTrivia"}
{"created_at":"2019-05-29T04:04:19.000Z","id":1133584832288526336,"text":"it’s just a little chapstick https://t.co/Ys0wm4wrgE","user_followers_count":804,"user_friends_count":276,"user_id":2824227905,"user_screen_name":"ThixxieMatteI"}
{"created_at":"2019-05-29T04:24:03.000Z","id":1133589798357217280,"text":"Not maintaining toxic family relationships is okay. Blood isn’t thicker than peace of mind","user_followers_count":947,"user_friends_count":511,"user_id":1039243531435614214,"user_screen_name":"JustFae_x"}
{"created_at":"2019-05-29T10:56:14.000Z","id":1133688494512103424,"text":"Brussels reshuffle: Ditte Juul-Jorgensen to become Director General for Energy in the European Commission. Followin… https://t.co/6052Hmydip","user_followers_count":3400,"user_friends_count":980,"user_id":216642693,"user_screen_name":"jonathangaventa"}
{"created_at":"2019-05-29T11:00:36.000Z","id":1133689593419640832,"text":"190526 TWICE World Tour in Seoul\n\nMVP🏅\n\n#TWICE #트와이스  #Sana #사나 https://t.co/jWogXwd5iq","user_followers_count":229,"user_friends_count":214,"user_id":921913213163266048,"user_screen_name":"wizon000hiss"}
{"created_at":"2019-05-29T14:09:43.000Z","id":1133737186187141121,"text":"sipsip nipples😉 and momol with Fighting Maroon Tripper https://t.co/d70DKxbESW","user_followers_count":70159,"user_friends_count":443,"user_id":891485789040685056,"user_screen_name":"MoanerBottom"}
{"created_at":"2019-05-29T22:41:46.000Z","id":1133866047772270592,"text":"This egg will light up the night! Catching lightning bugs were my favorite pass time as a kid so we had a blast des… https://t.co/H5dWbHH83C","user_followers_count":4614,"user_friends_count":279,"user_id":1551717960,"user_screen_name":"HawaiianSnowDev"}
{"created_at":"2019-05-30T03:27:47.000Z","id":1133938026239758336,"text":"Starting with the enlistment of Xiumin &amp; Do, other EXO members are also expected to join the military. the members… https://t.co/Z1GMOnL8Z5","user_followers_count":3379,"user_friends_count":347,"user_id":582703286,"user_screen_name":"confeito522"}
{"created_at":"2019-05-30T03:35:59.000Z","id":1133940089820798981,"text":"If you can't outplay them, outwork them. -Ben Hogan","user_followers_count":1189955,"user_friends_count":67958,"user_id":130684475,"user_screen_name":"Sports_Greats"}
{"created_at":"2019-05-30T12:19:13.000Z","id":1134071765821415424,"text":"bobby looked so amazed at the interpreter on the screen that he started dancing while watching hahdhs he cute :(… https://t.co/yufTl16OnN","user_followers_count":1571,"user_friends_count":695,"user_id":1054872833073930240,"user_screen_name":"ikoniconie"}
{"created_at":"2019-05-30T14:09:10.000Z","id":1134099435636633601,"text":"For 2 times i did that mistake ,, guess what !! I realize that after 2 years passed in each company","user_followers_count":289,"user_friends_count":231,"user_id":731097331194548224,"user_screen_name":"imado_3"}
{"created_at":"2019-05-30T14:51:39.000Z","id":1134110126900514816,"text":"feels like a good omen :) \n#BreathoftheWild #NintendoSwitch https://t.co/EuSAxciPHu","user_followers_count":4,"user_friends_count":84,"user_id":1126264674343735296,"user_screen_name":"Painfulexisten1"}
