{"created_at":"2019-06-15T12:55:47.000Z","id":1139879173957144576,"text":"#ThalapathyDayCommonCP \n#ThalapathyDayCommonCP \n#ThalapathyDayCommonCP \n#ThalapathyDayCommonCP… https://t.co/ndhrJOWnur","user_followers_count":322,"user_friends_count":875,"user_id":1015801449832275968,"user_screen_name":"Suryagmailcom14"}
{"created_at":"2019-06-15T14:39:12.000Z","id":1139905199622017026,"text":"“shiro was keith’s elementary teacher” truly wild how antis just make up shit lmao","user_followers_count":345,"user_friends_count":250,"user_id":1031138545249988609,"user_screen_name":"hokageshiro"}
{"created_at":"2019-06-15T15:54:46.000Z","id":1139924216596144129,"text":"#dogs FOUND #SanAntonio TX,USA, German Shepherd Dog, May.30/19, https://t.co/OkWivRNlJQ @LostDogTX","user_followers_count":11216,"user_friends_count":4045,"user_id":208553458,"user_screen_name":"HelpingLostPets"}
{"created_at":"2019-06-15T18:56:12.000Z","id":1139969875777085445,"text":"Giveaway time whit @BountyGG \n\n2 winners 2.5$ on https://t.co/3SBdW1pFdL\n\n   Rules\n   - Follow me and @BountyGG… https://t.co/BXVVKjW585","user_followers_count":694,"user_friends_count":91,"user_id":3469251419,"user_screen_name":"unnamed934"}
{"created_at":"2019-06-15T23:47:43.000Z","id":1140043238365118465,"text":"「 #HerYerdeSen #SelDem 」\nThey're Soooo Cutttte ❤ https://t.co/PF0seuVwId","user_followers_count":54,"user_friends_count":16,"user_id":999349282917572608,"user_screen_name":"vazileon"}
{"created_at":"2019-06-16T02:14:26.000Z","id":1140080160806490118,"text":"What the fuck is this? First of all I didn’t even take offence in THAT sense. It was just a boy dancing \n\nSecond. S… https://t.co/hdTmMFZoVW","user_followers_count":836,"user_friends_count":218,"user_id":894902696918097920,"user_screen_name":"lmnotAIex"}
{"created_at":"2019-06-16T07:30:16.000Z","id":1140159642892480514,"text":"The Office never gets old.","user_followers_count":1541,"user_friends_count":316,"user_id":2703271333,"user_screen_name":"ShotBy6ix"}
{"created_at":"2019-06-16T08:13:28.000Z","id":1140170514511609856,"text":"You are not safe until you are saved \nNo Jesus No Life","user_followers_count":6230,"user_friends_count":4815,"user_id":1120383815908831232,"user_screen_name":"mayorthesauce"}
{"created_at":"2019-06-16T08:20:22.000Z","id":1140172250974285825,"text":"No one else comes close to you\n\n@donnypangilinan @KissesDelavin \n\n#DONKISSTiDADhana4ever \n\n https://t.co/2vNwO74Kyi","user_followers_count":8288,"user_friends_count":37,"user_id":2845390784,"user_screen_name":"llll3ov3"}
{"created_at":"2019-06-16T10:29:59.000Z","id":1140204870072492032,"text":"It’s Father’s Day but in the @BritishArmy we give thanks everyday to all those we call dad: serving soldiers, suppo… https://t.co/kVw4rIGNT6","user_followers_count":18615,"user_friends_count":718,"user_id":2742205255,"user_screen_name":"ArmyInLondon"}
{"created_at":"2019-06-16T13:59:37.000Z","id":1140257625998651393,"text":"Much needed board. Everywhere👏 https://t.co/Q1ma7z2KIu","user_followers_count":6189,"user_friends_count":590,"user_id":3110227957,"user_screen_name":"siri_mysuru"}
{"created_at":"2019-06-16T15:02:57.000Z","id":1140273564366467072,"text":"YES QUEENS I’M READY\n\n#TheReVeFestivalD3 @RVsmtown\n#Zimzalabim #REDVELVET https://t.co/xtQWEobRzq","user_followers_count":23217,"user_friends_count":185,"user_id":1580455592,"user_screen_name":"wanwansforehead"}
{"created_at":"2019-06-16T16:00:38.000Z","id":1140288080852770822,"text":"Today I completed the #londontobrightonbikeride after only having bought a bike last month to commute to work 🚴😎🌊 https://t.co/HhMr0efaaE","user_followers_count":441,"user_friends_count":784,"user_id":1880435917,"user_screen_name":"CampbellGeog"}
{"created_at":"2019-06-16T20:02:26.000Z","id":1140348931815223298,"text":"Borderlands 2 Golden Key Codes - Xbox Only - Infinite Use\n20 Keys: 5TKTB - W3J9R - TK5CX - 5XT33 - ZBBWW \n25 Keys:… https://t.co/QLMiNIgymV","user_followers_count":715,"user_friends_count":746,"user_id":1902518930,"user_screen_name":"DarkInferno29"}
{"created_at":"2019-06-17T00:04:20.000Z","id":1140409807930658816,"text":"THE AMOUNT OF LOVE #taejin https://t.co/RejM0AVClS","user_followers_count":48,"user_friends_count":94,"user_id":1007128295387697152,"user_screen_name":"iamKINGseokjin"}
{"created_at":"2019-06-17T03:14:58.000Z","id":1140457782409420801,"text":"🗣️LAST CHANCE PERVS🗣️\n          PREMIUM SNAP $10/YR 😮\n                 Regular price $35!\nEnjoy seeing my pussy squ… https://t.co/dIlT01OEMW","user_followers_count":425,"user_friends_count":110,"user_id":1092893726849069062,"user_screen_name":"ohsoslumxxx"}
{"created_at":"2019-06-17T08:07:56.000Z","id":1140531509884964864,"text":"This is how the surface area of a sphere is calculated https://t.co/h0h2F3JgWI","user_followers_count":280937,"user_friends_count":196,"user_id":781427301472874497,"user_screen_name":"PhysicsVideo_"}
{"created_at":"2019-06-17T10:23:16.000Z","id":1140565567604252672,"text":"Great to see the EU’s sanctions regime for #Maldives lifted today – a sign of confidence in the country’s continued… https://t.co/ZRRxYV9ovR","user_followers_count":16984,"user_friends_count":290,"user_id":81857654,"user_screen_name":"MarkFieldUK"}
{"created_at":"2019-06-17T16:16:03.000Z","id":1140654348457992192,"text":"Supreme Court blocks suit over racially gerrymandered districts in Virginia. https://t.co/qua7Pm2Xmx","user_followers_count":6603625,"user_friends_count":1760,"user_id":14173315,"user_screen_name":"NBCNews"}
