{"created_at":"2019-03-24T11:03:48.000Z","id":1109772799604719617,"text":"We're here!\n\nSee you @bernardokath 👑\nThank you Mommy @min_bernardo ❤ 😘\n\nTHOU HighestGrossingFilm… https://t.co/kgGBvAS3p3","user_followers_count":5059,"user_friends_count":145,"user_id":725658372188430337,"user_screen_name":"KATHTropaOFC"}
{"created_at":"2019-03-24T19:25:24.000Z","id":1109899031348559872,"text":"Christ she doesn’t like women much does she ?","user_followers_count":453605,"user_friends_count":8336,"user_id":19644592,"user_screen_name":"campbellclaret"}
{"created_at":"2019-03-24T19:31:10.000Z","id":1109900482586136577,"text":"Man, fuck this. I'm tired of all these new twists on the same thinkpiece framework of \"I'm a smug, rude asshole. He… https://t.co/9UkzUOBgOT","user_followers_count":1302,"user_friends_count":289,"user_id":559835372,"user_screen_name":"ObeseChess"}
{"created_at":"2019-03-24T19:53:21.000Z","id":1109906064584200193,"text":"Don Jr. Goes Full Douche During Sunday Afternoon Mueller Report Tantrum https://t.co/IDhFjKMZjW","user_followers_count":149086,"user_friends_count":44474,"user_id":487600344,"user_screen_name":"Bipartisanism"}
{"created_at":"2019-03-24T21:12:33.000Z","id":1109925996550123521,"text":"Good point. Harnessing yesterday's middle England enthusiasms should be priority for nay party interested in power.… https://t.co/nUmDYA7LTX","user_followers_count":16879,"user_friends_count":630,"user_id":79737242,"user_screen_name":"DenisMacShane"}
{"created_at":"2019-03-24T21:57:05.000Z","id":1109937203730366467,"text":"i've never really cared (or tweeted much) about russia stuff but impulse of some media types to take a victory lap… https://t.co/x16B1PPn5X","user_followers_count":16241,"user_friends_count":754,"user_id":310677505,"user_screen_name":"kept_simple"}
